README.rst
setup.py
aio/__init__.py
aio.testing.egg-info/PKG-INFO
aio.testing.egg-info/SOURCES.txt
aio.testing.egg-info/dependency_links.txt
aio.testing.egg-info/entry_points.txt
aio.testing.egg-info/namespace_packages.txt
aio.testing.egg-info/not-zip-safe
aio.testing.egg-info/requires.txt
aio.testing.egg-info/top_level.txt
aio/testing/__init__.py
aio/testing/contextmanagers.py
aio/testing/tests/__init__.py
aio/testing/tests/test_contextmanagers.py