Metadata-Version: 1.1
Name: aio.testing
Version: 0.0.1
Summary: Asyncio testing utils
Home-page: http://github.com/phlax/aio.testing
Author: Ryan Northey
Author-email: ryan@3ca.org.uk
License: GPL
Platform: UNKNOWN
Classifier: Development Status :: 4 - Beta
Classifier: Intended Audience :: Developers
Classifier: Programming Language :: Python :: 3.4
Classifier: Topic :: Software Development :: Libraries :: Python Modules
